{
  "id": "7even-sins",
  "name": "7even Sins",
  "dateAdded": "2026-01-14T09:50:37.322Z",
  "dateUpdated": null,
  "removed": false,
  "issue": null,
  "disclosure": "none",
  "disclosureTypes": [],
  "urls": [],
  "markers": [
    "ai-visuals",
    "anonymous"
  ],
  "notes": null,
  "genres": [],
  "popularity": null,
  "followers": null,
  "shScore": null,
  "spotify": "0Z4s72zVZ26SCi5auS4Lwv",
  "apple": "1775450423",
  "amazon": "B09TY7ZQ8R",
  "youtube": "UCfXUOEgx-767Ra2rr9zIVzQ",
  "tiktok": "@7evensins.official",
  "instagram": "7evensins.official"
}
