{
  "id": "abscond",
  "name": "abscond",
  "dateAdded": "2026-01-16T13:43:54.334Z",
  "dateUpdated": null,
  "removed": false,
  "issue": null,
  "disclosure": "none",
  "disclosureTypes": [],
  "urls": [],
  "markers": [
    "anonymous"
  ],
  "notes": null,
  "genres": [],
  "popularity": null,
  "followers": null,
  "shScore": null,
  "spotify": "1I3whUpIkMLTIDkEaETcHe",
  "apple": "1859916840",
  "amazon": "B084QFKKMV",
  "youtube": "UCJ7Gt8z5sPFZeWVSqjFz_8w",
  "tiktok": "@absc_nd",
  "instagram": "asbc_nd"
}
