{
  "id": "aleister-temple",
  "name": "Aleister Temple",
  "dateAdded": "2025-11-25T12:12:56.000Z",
  "dateUpdated": "2026-01-20T13:18:16.965Z",
  "removed": false,
  "issue": null,
  "disclosure": "none",
  "disclosureTypes": [],
  "urls": [],
  "markers": [
    "anonymous",
    "high-output"
  ],
  "notes": "No information or photos of members; generic AI art",
  "genres": [],
  "popularity": null,
  "followers": null,
  "shScore": null,
  "spotify": "0EVrCbMQybkg7m8vZFbQTJ",
  "apple": "1845876599",
  "amazon": "B0FHGHH2K5",
  "youtube": "UCF_qMG5PdFsis19wt57AI5w",
  "tiktok": null,
  "instagram": null
}
