{
  "id": "ashes-of-angst",
  "name": "Ashes of Angst",
  "dateAdded": "2025-11-25T12:12:56.000Z",
  "dateUpdated": null,
  "disclosure": "none",
  "disclosureNotes": null,
  "disclosureTypes": [],
  "markers": [],
  "markerNotes": "AI Vocals",
  "genres": [],
  "popularity": null,
  "followers": null,
  "shScore": null,
  "spotify": "2UJm5tXcmflQFMi6hPyzvn",
  "apple": "1502978102",
  "amazon": null,
  "youtube": "UC_7_SdkKNb021MFsqVvhWqQ",
  "tiktok": null,
  "instagram": "ashesofangstofficial"
}
