{
  "id": "courland-static",
  "name": "Courland Static",
  "dateAdded": "2026-01-27T23:18:40.676Z",
  "dateUpdated": null,
  "removed": false,
  "issue": null,
  "disclosure": "confirmed",
  "disclosureTypes": [],
  "urls": [],
  "markers": [
    "ai-visuals"
  ],
  "notes": "The Spotify bio states: \"One person writing everything, teaming up with AI to turn Baltic gloom, concrete and late-night thoughts into loud, melodic chaos.\"",
  "genres": [],
  "popularity": null,
  "followers": null,
  "shScore": null,
  "spotify": "2zTn8pnqGFQKo6fDnkrzfj",
  "apple": null,
  "amazon": null,
  "youtube": null,
  "tiktok": "@courlandstatic",
  "instagram": "courlandstatic"
}
