{
  "id": "enkisoul",
  "name": "Enkisoul",
  "dateAdded": "2026-01-07T14:07:39.052Z",
  "dateUpdated": null,
  "disclosure": "none",
  "disclosureNotes": null,
  "disclosureTypes": [],
  "markers": [
    "ai-visuals",
    "high-output"
  ],
  "markerNotes": "Self acknowledges as an AI-generated band on YouTube.",
  "genres": [],
  "popularity": null,
  "followers": null,
  "shScore": null,
  "spotify": "5PSrqODnWGpcCwajIOZJK7",
  "apple": "1738828359",
  "amazon": "B0CZJY4WG5",
  "youtube": "UCTwAt-jRNl1NqIrtXIdRJZA",
  "tiktok": "@enkisoulmusic",
  "instagram": "enkisoulmusic"
}
