{
  "id": "ghost-signal",
  "name": "Ghost//Signal",
  "dateAdded": "2025-12-13T22:15:02.000Z",
  "dateUpdated": "2026-01-31T21:06:41.522Z",
  "removed": false,
  "issue": 2704,
  "disclosure": "none",
  "disclosureTypes": [],
  "urls": [],
  "markers": [
    "2024-onwards",
    "ai-visuals"
  ],
  "notes": null,
  "genres": [],
  "popularity": null,
  "followers": null,
  "shScore": null,
  "spotify": "1MSx7eCIGLByF6My5VMgrH",
  "apple": "1820841282",
  "amazon": "B0FD9JLZ4Z",
  "youtube": "UC4D_GXejDXWtkH8gqRL3H1w",
  "tiktok": null,
  "instagram": null
}
