{
  "id": "hazy-thompson",
  "name": "Hazy Thompson",
  "dateAdded": "2026-01-18T21:33:29.722Z",
  "dateUpdated": null,
  "disclosure": "none",
  "disclosureNotes": null,
  "disclosureTypes": [],
  "markers": [
    "ai-visuals",
    "anonymous"
  ],
  "markerNotes": "The artist has a profile under the username @jlpenman on the Suno website.",
  "comments": "The artist has a profile under the username @jlpenman on the Suno website.",
  "tags": [
    "ai-visuals",
    "audio-artifacts",
    "anonymous",
    "no-social-presence"
  ],
  "genres": [],
  "popularity": null,
  "followers": null,
  "shScore": null,
  "spotify": "5JIhg8TzXNTYj0RN0Y2O30",
  "apple": "1824920012",
  "amazon": "B0FGW6T51S",
  "youtube": "UC577Ojw7jqcAZnu1CLFmW_A",
  "tiktok": null,
  "instagram": "hazythompsonmusic"
}
