{
  "id": "heaven-groove-and-soul",
  "name": "Heaven Groove & Soul",
  "dateAdded": "2025-12-20T11:58:47.000Z",
  "dateUpdated": null,
  "disclosure": "none",
  "disclosureNotes": null,
  "disclosureTypes": [],
  "markers": [],
  "markerNotes": "Brazilian / Portuguese Christian AI slop",
  "genres": [],
  "popularity": null,
  "followers": null,
  "shScore": null,
  "spotify": "50leWS5dVkkyUCClW19JzY",
  "apple": "1848208184",
  "amazon": "B0FX5BFR87",
  "youtube": "@HeavenGrooveSoul",
  "tiktok": "@heavengroovesoul",
  "instagram": "heavengroovesoul"
}
