{
  "id": "kingslove",
  "name": "Kingslove",
  "dateAdded": "2026-01-10T10:52:16.211Z",
  "dateUpdated": null,
  "removed": false,
  "issue": null,
  "disclosure": "none",
  "disclosureTypes": [],
  "urls": [],
  "markers": [
    "ai-visuals",
    "anonymous"
  ],
  "notes": null,
  "genres": [],
  "popularity": null,
  "followers": null,
  "shScore": null,
  "spotify": "66iRXtLQbPVHOMlCVEoM7c",
  "apple": "1812430198",
  "amazon": "B007YOPO4M",
  "youtube": "UCmMYWyBOp0l-pSCO1XwGw_A",
  "tiktok": null,
  "instagram": null
}
