{
  "id": "kuroshibapalette",
  "name": "kuroshibapalette",
  "dateAdded": "2026-02-14T16:56:58.561Z",
  "dateUpdated": null,
  "removed": false,
  "issue": null,
  "disclosure": "full",
  "disclosureNotes": "YouTube channel description states: \"AI Music & AI Video  by Kuroshibapalette.\"",
  "disclosureTypes": [],
  "urls": [],
  "markers": [
    "ai-visuals",
    "anonymous",
    "high-output",
    "inconsistent-style",
    "2024-onwards"
  ],
  "markerNotes": null,
  "genres": [],
  "popularity": null,
  "followers": null,
  "shScore": null,
  "spotify": "0OFXacOlqEejo9tCfS20iP",
  "apple": "1816232768",
  "amazon": "B0F9L5FXS7",
  "youtube": "UCUmZKjaaFxao9lzozxSGd1w",
  "tiktok": "@kuroshibapalette1029",
  "instagram": "kuroshiba_palette1029"
}
