{
  "id": "meridian-shore",
  "name": "Meridian Shore",
  "dateAdded": "2026-01-25T21:02:11.689Z",
  "dateUpdated": null,
  "removed": false,
  "issue": null,
  "disclosure": "confirmed",
  "disclosureTypes": [],
  "urls": [],
  "markers": [
    "ai-visuals",
    "anonymous",
    "high-output"
  ],
  "notes": "The YouTube bio states: \"An emotional post-hardcore project combining real, vulnerable lyrics with AI-assisted instrumentation and vocals.\"",
  "genres": [],
  "popularity": null,
  "followers": null,
  "shScore": null,
  "spotify": "48Jp2EWuUpwI1FljrLrJZC",
  "apple": "1859431710",
  "amazon": "B0G5M7W964",
  "youtube": "UC4ZiDPLA-nIS5Z3aUZjCjgw",
  "tiktok": "@meridian.shore",
  "instagram": null
}
