{
  "id": "moonshine-outlaws",
  "name": "Moonshine Outlaws",
  "dateAdded": "2025-12-08T10:49:35.000Z",
  "dateUpdated": null,
  "removed": false,
  "issue": null,
  "disclosure": "none",
  "disclosureTypes": [],
  "urls": [],
  "markers": [
    "anonymous",
    "high-output"
  ],
  "notes": null,
  "genres": [],
  "popularity": null,
  "followers": null,
  "shScore": null,
  "spotify": "4NBzZZiV31JXgF8R4IvBAr",
  "apple": "1838538725",
  "amazon": "B0FQ7YHJ3K",
  "youtube": "UC2vq0pm_W64k0RDqk8siO6w",
  "tiktok": null,
  "instagram": "moonshineoutlaws"
}
