{
  "id": "my-boy-arlo",
  "name": "My Boy Arlo",
  "dateAdded": "2026-01-13T21:53:21.594Z",
  "dateUpdated": null,
  "disclosure": "confirmed",
  "disclosureNotes": "YouTube bio states the project is \"where human creativity meets digital storytelling.\" The Instagram and TikTok bios also states: \"Human creativity meets digital rhythm.\"",
  "disclosureTypes": [],
  "markers": [
    "high-output"
  ],
  "markerNotes": null,
  "comments": "YouTube bio states the project is \"where human creativity meets digital storytelling.\" The Instagram and TikTok bios also states: \"Human creativity meets digital rhythm.\"",
  "tags": [
    "audio-artifacts",
    "high-output",
    "partial-ai",
    "self-disclosed-ai"
  ],
  "genres": [],
  "popularity": null,
  "followers": null,
  "shScore": null,
  "spotify": "7jnEJXIT7Ur1VLF1BC48eD",
  "apple": "1848819247",
  "amazon": "B0FXXLFM2P",
  "youtube": "@MyBoyArlo",
  "tiktok": "@myboyarlo",
  "instagram": "myboyarlomusic"
}
