{
  "id": "ol-man-yarn",
  "name": "Ol Man Yarn",
  "dateAdded": "2026-01-10T11:14:41.721Z",
  "dateUpdated": null,
  "removed": false,
  "issue": null,
  "disclosure": "none",
  "disclosureTypes": [],
  "urls": [],
  "markers": [
    "ai-visuals",
    "anonymous"
  ],
  "notes": null,
  "genres": [],
  "popularity": null,
  "followers": null,
  "shScore": null,
  "spotify": "6Qh45YYljqKFN9yWJG2P2F",
  "apple": "1841467090",
  "amazon": "B0FS4NCSFG",
  "youtube": "UCDZx_1DBz6FM-r5bx8JVgzA",
  "tiktok": "@olmanyarn",
  "instagram": "olmanyarn"
}
