{
  "id": "puppet-spider",
  "name": "Puppet Spider",
  "dateAdded": "2025-11-26T09:26:43.000Z",
  "dateUpdated": null,
  "removed": false,
  "issue": null,
  "disclosure": "none",
  "disclosureNotes": null,
  "disclosureTypes": [],
  "urls": [],
  "markers": [],
  "markerNotes": null,
  "genres": [],
  "popularity": null,
  "followers": null,
  "shScore": null,
  "spotify": "5MlG9IL96nYF58A8jsYu9D",
  "apple": null,
  "amazon": null,
  "youtube": "UCwB1A1rOUiJ87LQ6DtBiemA",
  "tiktok": null,
  "instagram": null
}
