{
  "id": "santino-ray",
  "name": "Santino Ray",
  "dateAdded": "2026-02-05T14:32:42.572Z",
  "dateUpdated": null,
  "removed": false,
  "issue": 3002,
  "disclosure": "none",
  "disclosureTypes": [],
  "urls": [],
  "markers": [
    "2024-onwards",
    "ai-visuals",
    "anonymous",
    "high-output"
  ],
  "notes": null,
  "genres": [],
  "popularity": null,
  "followers": null,
  "shScore": null,
  "spotify": "6zxb6jNn1Su1E2AVcOMNfN",
  "apple": "1854661828",
  "amazon": null,
  "youtube": "UCdRTm_oJFG9AUkoo6GTw5Lw",
  "tiktok": null,
  "instagram": null
}
