{
  "id": "sons-of-ashes",
  "name": "Sons of Ashes",
  "dateAdded": "2025-12-14T12:23:44.000Z",
  "dateUpdated": null,
  "removed": false,
  "issue": null,
  "disclosure": "none",
  "disclosureTypes": [],
  "urls": [],
  "markers": [
    "anonymous",
    "high-output"
  ],
  "notes": null,
  "genres": [],
  "popularity": null,
  "followers": null,
  "shScore": null,
  "spotify": "5Mi7UZZa3v6zZ1wbrij1Rj",
  "apple": "1829185494",
  "amazon": "B0FK3793JC",
  "youtube": "UCjGZ68pz9zgvxtQz3_C22SA",
  "tiktok": "@sonsofashes",
  "instagram": "sonsofashes"
}
