{
  "id": "theskeletonslibrary",
  "name": "TheSkeletonsLibrary",
  "dateAdded": "2025-12-10T17:16:34.000Z",
  "dateUpdated": "2026-01-14T09:44:52.640Z",
  "disclosure": "confirmed",
  "disclosureNotes": "Spotify bio states: \"The Skeletons Library is a modern metal project built on real human emotion and brought to life through the power of AI.\"",
  "disclosureTypes": [],
  "markers": [
    "ai-visuals",
    "anonymous"
  ],
  "markerNotes": null,
  "genres": [],
  "popularity": null,
  "followers": null,
  "shScore": null,
  "spotify": "49yWNU05MepSpoYQTKADro",
  "apple": "1856929698",
  "amazon": "B0G345454G",
  "youtube": "UCLMbY1s9n-wnqpbwEyBZZnQ",
  "tiktok": "@theskeletonslibrary",
  "instagram": "theskeletonslibrary"
}
